deprecated_crypt_alternative-0.1.2.dist-info/METADATA
deprecated_crypt_alternative-0.1.2.dist-info/WHEEL
_crypt.libs/libcrypt-bb0d1e0f.so.2
_crypt/__init__.py
_crypt/_crypt.abi3.so
deprecated_crypt_alternative-0.1.2.dist-info/RECORD
